<?xml version="1.0" encoding="UTF-8"?><record_update table="pa_dashboards_permissions">
    <pa_dashboards_permissions action="INSERT_OR_UPDATE">
        <dashboard display_value="Context Sensitive Analytics - CS">b86af816eb0112001e68286b1206fe45</dashboard>
        <delete>false</delete>
        <group/>
        <identity>pa_contributor</identity>
        <read>true</read>
        <role display_value="pa_contributor" name="pa_contributor">aeec30b3bf101100b96dac808c073943</role>
        <sys_class_name>pa_dashboards_permissions</sys_class_name>
        <sys_created_by>admin</sys_created_by>
        <sys_created_on>2023-04-03 10:46:35</sys_created_on>
        <sys_id>26867fd81b06e1505bdeed71f54bcbfc</sys_id>
        <sys_mod_count>0</sys_mod_count>
        <sys_name>pa_contributor</sys_name>
        <sys_package display_value="Support case" source="x_liisa_support_ca">80d47c06dba7f05001eafad3f3961926</sys_package>
        <sys_policy/>
        <sys_scope display_value="Support case">80d47c06dba7f05001eafad3f3961926</sys_scope>
        <sys_update_name>pa_dashboards_permissions_26867fd81b06e1505bdeed71f54bcbfc</sys_update_name>
        <sys_updated_by>admin</sys_updated_by>
        <sys_updated_on>2023-04-03 10:46:35</sys_updated_on>
        <type>1</type>
        <user/>
        <write>false</write>
    </pa_dashboards_permissions>
</record_update>
